{
    "type": "mysql",
    "host": "localhost",
    "port": 3306,
    "username": "root",
    "password": "password",
    "database": "site_typescript",
    "synchronize": true,
    "logging": false,
    "entities": [
        "database/src/entity/**/*{.ts}"
    ],
    "migrations": [
        "database/src/migrations/**/*{.ts}"
    ],
    "subscriber": [
        "database/src/subscriber/**/*{.ts}"
    ],
    "cli":{
        "entitiesDir": "database/src/entity",
        "migrationsDir": "database/src/migration",
        "subscribersDir": "database/src/subscriber"
    } 
}